student_ai_kit/__init__.py
student_ai_kit/ai_tools.py
student_ai_kit_hafizmdph-0.1.0.dist-info/METADATA
student_ai_kit_hafizmdph-0.1.0.dist-info/WHEEL
student_ai_kit_hafizmdph-0.1.0.dist-info/top_level.txt
student_ai_kit_hafizmdph-0.1.0.dist-info/RECORD
