Metadata-Version: 2.4
Name: student_ai_kit_hafizmdph
Version: 0.1.0
Summary: A helper library for AI text processing and API communication
Author: Student Name
Classifier: Programming Language :: Python :: 3
Classifier: License :: OSI Approved :: MIT License
Classifier: Operating System :: OS Independent
Requires-Python: >=3.6
Requires-Dist: requests
Dynamic: author
Dynamic: classifier
Dynamic: description
Dynamic: description-content-type
Dynamic: requires-dist
Dynamic: requires-python
Dynamic: summary
